krystal/__init__.py
krystal/main.py
krystal-2.0.1.dist-info/LICENSE
krystal-2.0.1.dist-info/METADATA
krystal-2.0.1.dist-info/WHEEL
krystal-2.0.1.dist-info/entry_points.txt
krystal-2.0.1.dist-info/top_level.txt
krystal-2.0.1.dist-info/RECORD
