Metadata-Version: 2.1
Name: krystal
Version: 2.0.1
Summary: Krystal's static website builder
Home-page: https://github.com/krystalgamer/krystal
Author: krystalgamer
Author-email: krystalgamer@protonmail.com
License: UNKNOWN
Platform: UNKNOWN
License-File: LICENSE
Requires-Dist: Flask <3,>=2.0.3
Requires-Dist: Frozen-Flask ==0.18
Requires-Dist: Pygments ==2.16.1
Requires-Dist: Werkzeug <3
Requires-Dist: marko ==2.0.1
